<?xml version="1.0" encoding="utf-8" ?>
<INTERACTIONS>
<INTERACTION>
<SOURCE>
<CLINICAL_SOURCE>ANSM</CLINICAL_SOURCE>
<SOURCE_FILE>34-AMLODIPINE.html
</SOURCE_FILE>
</SOURCE>
<DRUG1>
<DRUG name="AMLODIPINE" rxcui="17767">
<ATC code="C08CA01" />
</DRUG>
</DRUG1>
<DRUG2>
<DRUG name="SIMVASTATIN" rxcui="36567">
<ATC code="C10AA01" />
</DRUG>
</DRUG2>
<DESCRIPTION>Increased risk of undesirable effects (dose dependent) of the rhabdomyolysis type (decrease of the hepatic metabolism of the cholesterol lowering medication).</DESCRIPTION>
<SEVERITY>Precaution for use</SEVERITY>
<COMMENT></COMMENT>
</INTERACTION>
</INTERACTIONS>
